exejs/__init__.py
exejs/config.py
exejs/runtimes.py
exejs-0.0.7.dist-info/licenses/LICENSE
exejs-0.0.7.dist-info/METADATA
exejs-0.0.7.dist-info/WHEEL
exejs-0.0.7.dist-info/top_level.txt
exejs-0.0.7.dist-info/RECORD
